setup.py
geepyjak/L8_add_EVI.py
geepyjak/L8_add_NDVI.py
geepyjak/L8_add_NDWI.py
geepyjak/S2_add_NDVI.py
geepyjak/S2_add_NDWI.py
geepyjak/__init__.py
geepyjak/maskL8.py
geepyjak/maskS2clouds.py
geepyjak/panSharpenL8.py
geepyjak.egg-info/PKG-INFO
geepyjak.egg-info/SOURCES.txt
geepyjak.egg-info/dependency_links.txt
geepyjak.egg-info/requires.txt
geepyjak.egg-info/top_level.txt