Metadata-Version: 2.1
Name: geepyjak
Version: 1.0.0
Summary: earth engine function imports
Home-page: UNKNOWN
Author: Antony Kishoare J
Author-email: <a060697.ak@gmail.com>
License: UNKNOWN
Keywords: ee,geepyjak
Platform: UNKNOWN
Classifier: Development Status :: 3 - Alpha
Classifier: Intended Audience :: Education
Classifier: Programming Language :: Python :: 2
Classifier: Programming Language :: Python :: 3
Classifier: Operating System :: MacOS :: MacOS X
Classifier: Operating System :: Microsoft :: Windows
